Caesar_Cipher/__init__.py
Caesar_Cipher/main.py
caesar_cipher2-0.1.dist-info/METADATA
caesar_cipher2-0.1.dist-info/WHEEL
caesar_cipher2-0.1.dist-info/top_level.txt
caesar_cipher2-0.1.dist-info/RECORD
